README.md
setup.py
AssemblyToC/__init__.py
OS_Maker.egg-info/PKG-INFO
OS_Maker.egg-info/SOURCES.txt
OS_Maker.egg-info/dependency_links.txt
OS_Maker.egg-info/entry_points.txt
OS_Maker.egg-info/top_level.txt
os_maker_compiler/__init__.py
os_maker_compiler/__main__.py