Metadata-Version: 2.1
Name: OS-Maker
Version: 1.0
Summary: Make OS with some languages
Home-page: 
Author: JonDev2023
Author-email: 
License: All Free
Classifier: Operating System :: POSIX :: Linux
